{
  "results": {
    "WTI": {
      "price": 87.98,
      "high": 88.4,
      "low": 87.32,
      "prevClose": 82.49,
      "name": "WTI Crude",
      "unit": "USD/bbl",
      "digits": 2
    },
    "BRENT": {
      "price": 95.67,
      "high": 96.06,
      "low": 94.88,
      "prevClose": 88.1,
      "name": "Brent Crude",
      "unit": "USD/bbl",
      "digits": 2
    },
    "COPPER": {
      "price": 6.4805,
      "high": 6.4875,
      "low": 6.4705,
      "prevClose": 6.22,
      "name": "Copper",
      "unit": "USD/lb",
      "digits": 2
    },
    "BTC": {
      "price": 66031.01,
      "high": 66236.625,
      "low": 66041.44,
      "prevClose": 64690.805,
      "name": "Bitcoin",
      "unit": "USD",
      "digits": 0
    },
    "EURUSD": {
      "price": 1.1418,
      "high": 1.1418,
      "low": 1.1409,
      "prevClose": 1.1445,
      "name": "EUR/USD",
      "unit": "",
      "digits": 4
    },
    "DXY": {
      "price": 101.107,
      "high": 101.125,
      "low": 101.093,
      "prevClose": 100.75,
      "name": "DXY",
      "unit": "",
      "digits": 2
    },
    "US10Y": {
      "price": 4.657,
      "high": 4.661,
      "low": 4.632,
      "prevClose": 4.569,
      "name": "US 10Y",
      "unit": "%",
      "digits": 2
    },
    "US3M": {
      "price": 3.745,
      "high": 3.753,
      "low": 3.73,
      "prevClose": 3.697,
      "name": "US 3M",
      "unit": "%",
      "digits": 2
    },
    "_SPREAD": {
      "value": 91.19999999999999,
      "name": "10Y-3M Spread",
      "unit": "bp"
    }
  },
  "prices": {
    "WTI": 87.98,
    "BRENT": 95.67,
    "COPPER": 6.4805,
    "BTC": 66031.01,
    "EURUSD": 1.1418,
    "DXY": 101.107,
    "US10Y": 4.657,
    "US3M": 3.745
  },
  "changes": {
    "WTI": {
      "abs": 5.490000000000009,
      "pct": 6.655352163898666
    },
    "BRENT": {
      "abs": 7.570000000000007,
      "pct": 8.592508513053357
    },
    "COPPER": {
      "abs": 0.2605000000000004,
      "pct": 4.188102893890682
    },
    "BTC": {
      "abs": 1340.2049999999945,
      "pct": 2.0717086454558644
    },
    "EURUSD": {
      "abs": -0.0027000000000001467,
      "pct": -0.2359108781127258
    },
    "DXY": {
      "abs": 0.3569999999999993,
      "pct": 0.3543424317617859
    },
    "US10Y": {
      "abs": 0.08800000000000008,
      "pct": 1.9260231998249087
    },
    "US3M": {
      "abs": 0.04800000000000004,
      "pct": 1.2983500135244805
    }
  },
  "timestamp": "2026-07-23T00:58:18.673Z",
  "fng": {
    "value": 31,
    "label": "Fear"
  }
}